LICENSE
MANIFEST.in
README.rst
setup.cfg
setup.py
fastapi_term_and_condition/__init__.py
fastapi_term_and_condition.egg-info/PKG-INFO
fastapi_term_and_condition.egg-info/SOURCES.txt
fastapi_term_and_condition.egg-info/dependency_links.txt
fastapi_term_and_condition.egg-info/requires.txt
fastapi_term_and_condition.egg-info/top_level.txt
fastapi_term_and_condition/api/__init__.py
fastapi_term_and_condition/api/deps.py
fastapi_term_and_condition/api/api_v1/__init__.py
fastapi_term_and_condition/api/api_v1/endpoints/__init__.py
fastapi_term_and_condition/api/api_v1/endpoints/term_and_condition.py
fastapi_term_and_condition/crud/__init__.py
fastapi_term_and_condition/crud/base.py
fastapi_term_and_condition/crud/crud.py
fastapi_term_and_condition/crud/crud_term_and_condition.py
fastapi_term_and_condition/exceptions/__init__.py
fastapi_term_and_condition/exceptions/base_exception.py
fastapi_term_and_condition/exceptions/public_exceptions.py
fastapi_term_and_condition/exceptions/util_exception.py
fastapi_term_and_condition/filters/__init__.py
fastapi_term_and_condition/filters/base_filter.py
fastapi_term_and_condition/filters/term_and_condition_filter.py
fastapi_term_and_condition/models/__init__.py
fastapi_term_and_condition/models/models.py
fastapi_term_and_condition/models/term_and_condition.py
fastapi_term_and_condition/orders/__init__.py
fastapi_term_and_condition/orders/base_order.py
fastapi_term_and_condition/schemas/__init__.py
fastapi_term_and_condition/schemas/base.py
fastapi_term_and_condition/schemas/schemas.py
fastapi_term_and_condition/schemas/term_and_condition.py